Metadata-Version: 2.1
Name: kanakfinalcalcy
Version: 0.0.1
Summary: this is a trial package used for calculation
Home-page: 
Author: Kanak RT
Author-email: kanakrt066@gmail.com
License: MIT
Platform: UNKNOWN
License-File: LICENCE.txt
